india_data_set/__init__.py
india_data_set/data_set.py
india_data_set-1.0.dist-info/LICENSE
india_data_set-1.0.dist-info/METADATA
india_data_set-1.0.dist-info/WHEEL
india_data_set-1.0.dist-info/top_level.txt
india_data_set-1.0.dist-info/RECORD
