Metadata-Version: 2.1
Name: india-data-set
Version: 1.0
Summary: This package is used to generate random names for testing purpose. Package is for educational purpose only.
Author-email: Bipin Tatkare <techbipinrt2526@gmail.com>
Classifier: Programming Language :: Python :: 3
Classifier: License :: OSI Approved :: MIT License
Classifier: Operating System :: OS Independent
Requires-Python: >=3.9
License-File: LICENSE
